py7dtd/__init__.py
py7dtd/version.py
py7dtd-1.0.0a0.dist-info/LICENSE
py7dtd-1.0.0a0.dist-info/METADATA
py7dtd-1.0.0a0.dist-info/WHEEL
py7dtd-1.0.0a0.dist-info/entry_points.txt
py7dtd-1.0.0a0.dist-info/top_level.txt
py7dtd-1.0.0a0.dist-info/RECORD
