Metadata-Version: 2.1
Name: py7dtd
Version: 1.0.0a0
Summary: Collection of 7 Days to Die bots, scripts and hacks
Home-page: https://github.com/tassoneroberto/py7dtd
Author: Roberto Tassone
Author-email: roberto.tassone@proton.me
License: MIT
Keywords: 7dtd,bots,hacks,scripts
Classifier: Development Status :: 2 - Pre-Alpha
Classifier: Intended Audience :: Developers
Classifier: Natural Language :: English
Classifier: Operating System :: Microsoft :: Windows
Classifier: Topic :: Software Development :: Build Tools
Classifier: Topic :: Software Development :: Libraries
Classifier: License :: OSI Approved :: MIT License
Classifier: Programming Language :: Python :: 3.7
License-File: LICENSE
Requires-Dist: pywin32 (==304)
Requires-Dist: pyWinhook (==1.6.2)
Requires-Dist: pillow (==7.0.0)
Provides-Extra: ai
Requires-Dist: tensorflow (==2.4.0) ; extra == 'ai'
Requires-Dist: tensorflow-gpu (==2.4.0) ; extra == 'ai'
Requires-Dist: keras (==2.4.3) ; extra == 'ai'
Requires-Dist: numpy (==1.19.3) ; extra == 'ai'
Requires-Dist: scipy (==1.4.1) ; extra == 'ai'
Requires-Dist: h5py (==2.10.0) ; extra == 'ai'
Requires-Dist: matplotlib (==3.3.2) ; extra == 'ai'
Requires-Dist: opencv-python (==4.5.5.64) ; extra == 'ai'
Requires-Dist: keras-resnet (==0.2.0) ; extra == 'ai'
Requires-Dist: imageai (==2.1.6) ; extra == 'ai'
Requires-Dist: labelImg (==1.8.3) ; extra == 'ai'
